[1,["4bxiNBw7tAHLwRGE3Hftwh","326jLtHQVI9I/J3C8ncPge","42ZVnIQmRP+ICDvHuauwBT","96T3m8Gz1KAIxtcNyvLGCY"],["_textureSetter"],["cc.SpriteFrame"],0,[[[{"name":"nutchon-an","rect":[0,0,243,59],"offset":[0,0],"originalSize":[243,59],"capInsets":[0,0,0,0]}],[0],0,[0],[0],[0]],[[{"name":"icon-tanloc","rect":[0,0,118,119],"offset":[0,0],"originalSize":[118,119],"capInsets":[0,0,0,0]}],[0],0,[0],[0],[1]],[[{"name":"btn_other","rect":[0,0,194,77],"offset":[0,0],"originalSize":[194,77],"capInsets":[85,0,83,0]}],[0],0,[0],[0],[2]],[[{"name":"icon-xinloc","rect":[0,0,118,119],"offset":[0,0],"originalSize":[118,119],"capInsets":[0,0,0,0]}],[0],0,[0],[0],[3]]]]